sqla_async_orm_queries/__init__.py
sqla_async_orm_queries/context.py
sqla_async_orm_queries/models.py
sqla_async_orm_queries-1.2.0.dist-info/LICENCE.md
sqla_async_orm_queries-1.2.0.dist-info/METADATA
sqla_async_orm_queries-1.2.0.dist-info/WHEEL
sqla_async_orm_queries-1.2.0.dist-info/RECORD
