Metadata-Version: 2.1
Name: sqla-async-orm-queries
Version: 1.2.0
Summary: Base model for SqlAlchemy async orm queries
Home-page: https://github.com/amrahhh/sqla_async_orm_queries
License: MIT
Author: Amrah
Author-email: bagirovemrah97@gmail.com
Requires-Python: >=3.8.2,<4.0.0
Classifier: Intended Audience :: Developers
Classifier: License :: OSI Approved :: MIT License
Classifier: Operating System :: OS Independent
Classifier: Programming Language :: Python
Classifier: Programming Language :: Python :: 3
Classifier: Programming Language :: Python :: 3.9
Classifier: Programming Language :: Python :: 3.10
Classifier: Programming Language :: Python :: 3.11
Classifier: Programming Language :: Python :: 3.12
Classifier: Programming Language :: Python :: 3 :: Only
Classifier: Programming Language :: Python :: 3.7
Classifier: Programming Language :: Python :: 3.8
Requires-Dist: asyncpg (>=0.28.0)
Requires-Dist: greenlet (>=3.0.3,<4.0.0)
Requires-Dist: sqlalchemy (>=2.0.21)
Project-URL: Repository, https://github.com/amrahhh/sqla_async_orm_queries
